<?xml version="1.0" encoding="UTF-8"?>

<!-- generated on 2025-05-29 08:49:35 by Eclipse SUMO sumo Version v1_20_0+0085-e155ab8699b
<configuration xmlns:xsi="http://www.w3.org/2001/XMLSchema-instance" xsi:noNamespaceSchemaLocation="http://sumo.dlr.de/xsd/sumoConfiguration.xsd">

    <input>
        <net-file value="../networks/roundabout.net.xml"/>
        <route-files value="../networks/routes1.rou.xml"/>
    </input>

    <output>
        <output-prefix value="13-"/>
        <battery-output.precision value="4"/>
        <tripinfo-output value="../networks/output_data/output_kan/tripinfo/tripinfo-output.xml"/>
        <collision-output value="../networks/output_data/output_kan/collision/collision-output.xml"/>
    </output>

    <time>
        <begin value="0"/>
        <step-length value="0.4"/>
    </time>

    <processing>
        <step-method.ballistic value="true"/>
        <lateral-resolution value="3.2"/>
        <collision.action value="warn"/>
        <collision.mingap-factor value="0"/>
        <time-to-teleport value="-1"/>
        <random-depart-offset value="5"/>
    </processing>

    <report>
        <no-warnings value="True"/>
        <no-step-log value="True"/>
    </report>

    <emissions>
        <device.emissions.probability value="1"/>
    </emissions>

    <battery>
        <device.battery.probability value="1"/>
    </battery>

    <traci_server>
        <remote-port value="47367"/>
    </traci_server>

    <gui_only>
        <quit-on-end value="True"/>
        <start value="True"/>
    </gui_only>

</configuration>
-->

<tripinfos xmlns:xsi="http://www.w3.org/2001/XMLSchema-instance" xsi:noNamespaceSchemaLocation="http://sumo.dlr.de/xsd/tripinfo_file.xsd">
    <tripinfo id="vehicle_79" depart="1.60" departLane="road0_0" departPos="4.10" departPosLat="0.00" departSpeed="5.29" departDelay="0.39" arrival="16.00" arrivalLane="-road3_0" arrivalPos="19.96" arrivalPosLat="0.00" arrivalSpeed="11.61" duration="14.40" routeLength="122.77" waitingTime="0.00" waitingCount="0" stopTime="0.00" timeLoss="4.27" rerouteNo="0" devices="tripinfo_vehicle_79 emissions_vehicle_79 battery_vehicle_79" vType="human" speedFactor="1.09" vaporized="">
        <emissions CO_abs="0" CO2_abs="0" HC_abs="0" PMx_abs="0" NOx_abs="0" fuel_abs="0" electricity_abs="53.486625"/>
    </tripinfo>
    <tripinfo id="vehicle_48" depart="0.40" departLane="road3_0" departPos="4.10" departPosLat="0.00" departSpeed="8.65" departDelay="0.10" arrival="16.40" arrivalLane="-road2_0" arrivalPos="19.96" arrivalPosLat="0.00" arrivalSpeed="11.20" duration="16.00" routeLength="122.77" waitingTime="0.00" waitingCount="0" stopTime="0.00" timeLoss="4.16" rerouteNo="1" devices="tripinfo_vehicle_48 routing_vehicle_48 emissions_vehicle_48 battery_vehicle_48" vType="human" speedFactor="0.88" vaporized="">
        <emissions CO_abs="0" CO2_abs="0" HC_abs="0" PMx_abs="0" NOx_abs="0" fuel_abs="0" electricity_abs="34.905033"/>
    </tripinfo>
    <tripinfo id="vehicle_3" depart="2.80" departLane="road0_0" departPos="4.10" departPosLat="0.00" departSpeed="4.68" departDelay="0.22" arrival="18.40" arrivalLane="-road3_0" arrivalPos="19.96" arrivalPosLat="0.00" arrivalSpeed="12.64" duration="15.60" routeLength="122.77" waitingTime="0.00" waitingCount="0" stopTime="0.00" timeLoss="5.12" rerouteNo="0" devices="tripinfo_vehicle_3 emissions_vehicle_3 battery_vehicle_3" vType="human" speedFactor="1.08" vaporized="">
        <emissions CO_abs="0" CO2_abs="0" HC_abs="0" PMx_abs="0" NOx_abs="0" fuel_abs="0" electricity_abs="59.776175"/>
    </tripinfo>
    <tripinfo id="vehicle_84" depart="2.40" departLane="road2_0" departPos="4.10" departPosLat="0.00" departSpeed="1.99" departDelay="2.37" arrival="18.40" arrivalLane="-road1_0" arrivalPos="19.96" arrivalPosLat="0.00" arrivalSpeed="12.59" duration="16.00" routeLength="122.77" waitingTime="0.00" waitingCount="0" stopTime="0.00" timeLoss="5.96" rerouteNo="1" devices="tripinfo_vehicle_84 routing_vehicle_84 emissions_vehicle_84 battery_vehicle_84" vType="human" speedFactor="1.15" vaporized="">
        <emissions CO_abs="0" CO2_abs="0" HC_abs="0" PMx_abs="0" NOx_abs="0" fuel_abs="0" electricity_abs="65.672332"/>
    </tripinfo>
    <tripinfo id="vehicle_91" depart="4.80" departLane="road2_0" departPos="4.10" departPosLat="0.00" departSpeed="2.72" departDelay="4.19" arrival="22.00" arrivalLane="-road1_0" arrivalPos="19.96" arrivalPosLat="0.00" arrivalSpeed="11.21" duration="17.20" routeLength="122.77" waitingTime="0.00" waitingCount="0" stopTime="0.00" timeLoss="5.39" rerouteNo="1" devices="tripinfo_vehicle_91 routing_vehicle_91 emissions_vehicle_91 battery_vehicle_91" vType="human" speedFactor="0.89" vaporized="">
        <emissions CO_abs="0" CO2_abs="0" HC_abs="0" PMx_abs="0" NOx_abs="0" fuel_abs="0" electricity_abs="52.508778"/>
    </tripinfo>
    <tripinfo id="vehicle_82" depart="1.20" departLane="road2_0" departPos="4.10" departPosLat="0.00" departSpeed="5.17" departDelay="0.99" arrival="23.20" arrivalLane="-road0_0" arrivalPos="19.96" arrivalPosLat="0.00" arrivalSpeed="12.74" duration="22.00" routeLength="206.37" waitingTime="0.00" waitingCount="0" stopTime="0.00" timeLoss="5.57" rerouteNo="1" devices="tripinfo_vehicle_82 routing_vehicle_82 emissions_vehicle_82 battery_vehicle_82" vType="human" speedFactor="1.02" vaporized="">
        <emissions CO_abs="0" CO2_abs="0" HC_abs="0" PMx_abs="0" NOx_abs="0" fuel_abs="0" electricity_abs="80.421092"/>
    </tripinfo>
    <tripinfo id="vehicle_12" depart="0.40" departLane="road2_0" departPos="4.10" departPosLat="0.00" departSpeed="9.48" departDelay="0.38" arrival="27.60" arrivalLane="-road3_0" arrivalPos="19.96" arrivalPosLat="0.00" arrivalSpeed="13.13" duration="27.20" routeLength="289.97" waitingTime="0.00" waitingCount="0" stopTime="0.00" timeLoss="4.91" rerouteNo="1" devices="tripinfo_vehicle_12 routing_vehicle_12 emissions_vehicle_12 battery_vehicle_12" vType="human" speedFactor="1.05" vaporized="">
        <emissions CO_abs="0" CO2_abs="0" HC_abs="0" PMx_abs="0" NOx_abs="0" fuel_abs="0" electricity_abs="88.010040"/>
    </tripinfo>
    <tripinfo id="vehicle_94" depart="4.00" departLane="road0_0" departPos="4.10" departPosLat="0.00" departSpeed="2.87" departDelay="0.95" arrival="27.60" arrivalLane="-road2_0" arrivalPos="19.96" arrivalPosLat="0.00" arrivalSpeed="12.11" duration="23.60" routeLength="206.37" waitingTime="0.00" waitingCount="0" stopTime="0.00" timeLoss="7.62" rerouteNo="0" devices="tripinfo_vehicle_94 emissions_vehicle_94 battery_vehicle_94" vType="human" speedFactor="1.09" vaporized="">
        <emissions CO_abs="0" CO2_abs="0" HC_abs="0" PMx_abs="0" NOx_abs="0" fuel_abs="0" electricity_abs="76.124247"/>
    </tripinfo>
    <tripinfo id="vehicle_93" depart="5.20" departLane="road3_0" departPos="4.10" departPosLat="0.00" departSpeed="1.96" departDelay="1.15" arrival="29.20" arrivalLane="-road1_0" arrivalPos="19.96" arrivalPosLat="0.00" arrivalSpeed="12.16" duration="24.00" routeLength="206.37" waitingTime="0.00" waitingCount="0" stopTime="0.00" timeLoss="6.02" rerouteNo="1" devices="tripinfo_vehicle_93 routing_vehicle_93 emissions_vehicle_93 battery_vehicle_93" vType="human" speedFactor="0.92" vaporized="">
        <emissions CO_abs="0" CO2_abs="0" HC_abs="0" PMx_abs="0" NOx_abs="0" fuel_abs="0" electricity_abs="79.592939"/>
    </tripinfo>
    <tripinfo id="vehicle_116" depart="3.20" departLane="road1_0" departPos="4.10" departPosLat="0.00" departSpeed="2.82" departDelay="0.37" arrival="30.00" arrivalLane="-road2_0" arrivalPos="19.96" arrivalPosLat="0.00" arrivalSpeed="12.23" duration="26.80" routeLength="289.97" waitingTime="0.00" waitingCount="0" stopTime="0.00" timeLoss="4.76" rerouteNo="1" devices="tripinfo_vehicle_116 routing_vehicle_116 emissions_vehicle_116 battery_vehicle_116" vType="human" speedFactor="1.18" vaporized="">
        <emissions CO_abs="0" CO2_abs="0" HC_abs="0" PMx_abs="0" NOx_abs="0" fuel_abs="0" electricity_abs="104.625143"/>
    </tripinfo>
    <tripinfo id="vehicle_58" depart="7.60" departLane="road3_0" departPos="4.10" departPosLat="0.00" departSpeed="2.36" departDelay="2.87" arrival="31.60" arrivalLane="-road1_0" arrivalPos="19.96" arrivalPosLat="0.00" arrivalSpeed="13.40" duration="24.00" routeLength="206.37" waitingTime="0.00" waitingCount="0" stopTime="0.00" timeLoss="7.39" rerouteNo="1" devices="tripinfo_vehicle_58 routing_vehicle_58 emissions_vehicle_58 battery_vehicle_58" vType="human" speedFactor="1.02" vaporized="">
        <emissions CO_abs="0" CO2_abs="0" HC_abs="0" PMx_abs="0" NOx_abs="0" fuel_abs="0" electricity_abs="86.627788"/>
    </tripinfo>
    <tripinfo id="vehicle_53" depart="10.00" departLane="road0_0" departPos="4.10" departPosLat="0.00" departSpeed="1.42" departDelay="4.62" arrival="32.00" arrivalLane="-road3_0" arrivalPos="19.96" arrivalPosLat="0.00" arrivalSpeed="11.73" duration="22.00" routeLength="122.77" waitingTime="0.00" waitingCount="0" stopTime="0.00" timeLoss="11.89" rerouteNo="0" devices="tripinfo_vehicle_53 emissions_vehicle_53 battery_vehicle_53" vType="human" speedFactor="1.10" vaporized="">
        <emissions CO_abs="0" CO2_abs="0" HC_abs="0" PMx_abs="0" NOx_abs="0" fuel_abs="0" electricity_abs="57.402735"/>
    </tripinfo>
    <tripinfo id="vehicle_38" depart="1.20" departLane="road3_0" departPos="4.10" departPosLat="0.00" departSpeed="3.63" departDelay="0.48" arrival="34.80" arrivalLane="-road0_0" arrivalPos="19.96" arrivalPosLat="0.00" arrivalSpeed="13.52" duration="33.60" routeLength="289.97" waitingTime="0.00" waitingCount="0" stopTime="0.00" timeLoss="11.27" rerouteNo="1" devices="tripinfo_vehicle_38 routing_vehicle_38 emissions_vehicle_38 battery_vehicle_38" vType="human" speedFactor="1.10" vaporized="">
        <emissions CO_abs="0" CO2_abs="0" HC_abs="0" PMx_abs="0" NOx_abs="0" fuel_abs="0" electricity_abs="101.196626"/>
    </tripinfo>
    <tripinfo id="vehicle_72" depart="21.20" departLane="road0_0" departPos="4.10" departPosLat="0.00" departSpeed="2.42" departDelay="12.39" arrival="38.40" arrivalLane="-road3_0" arrivalPos="19.96" arrivalPosLat="0.00" arrivalSpeed="11.99" duration="17.20" routeLength="122.77" waitingTime="0.00" waitingCount="0" stopTime="0.00" timeLoss="6.30" rerouteNo="0" devices="tripinfo_vehicle_72 emissions_vehicle_72 battery_vehicle_72" vType="human" speedFactor="0.94" vaporized="">
        <emissions CO_abs="0" CO2_abs="0" HC_abs="0" PMx_abs="0" NOx_abs="0" fuel_abs="0" electricity_abs="58.118032"/>
    </tripinfo>
    <tripinfo id="vehicle_101" depart="2.80" departLane="road3_0" departPos="4.10" departPosLat="0.00" departSpeed="1.37" departDelay="0.39" arrival="39.60" arrivalLane="-road0_0" arrivalPos="19.96" arrivalPosLat="0.00" arrivalSpeed="12.02" duration="36.80" routeLength="289.97" waitingTime="0.00" waitingCount="0" stopTime="0.00" timeLoss="13.65" rerouteNo="1" devices="tripinfo_vehicle_101 routing_vehicle_101 emissions_vehicle_101 battery_vehicle_101" vType="human" speedFactor="0.96" vaporized="">
        <emissions CO_abs="0" CO2_abs="0" HC_abs="0" PMx_abs="0" NOx_abs="0" fuel_abs="0" electricity_abs="91.927426"/>
    </tripinfo>
    <tripinfo id="vehicle_86" depart="6.00" departLane="road0_0" departPos="4.10" departPosLat="0.00" departSpeed="2.88" departDelay="1.33" arrival="40.40" arrivalLane="-road1_0" arrivalPos="19.96" arrivalPosLat="0.00" arrivalSpeed="13.37" duration="34.40" routeLength="289.97" waitingTime="2.80" waitingCount="1" stopTime="0.00" timeLoss="11.87" rerouteNo="0" devices="tripinfo_vehicle_86 emissions_vehicle_86 battery_vehicle_86" vType="human" speedFactor="1.00" vaporized="">
        <emissions CO_abs="0" CO2_abs="0" HC_abs="0" PMx_abs="0" NOx_abs="0" fuel_abs="0" electricity_abs="108.932397"/>
    </tripinfo>
    <tripinfo id="vehicle_111" depart="4.40" departLane="road1_0" departPos="4.10" departPosLat="0.00" departSpeed="3.83" departDelay="0.50" arrival="40.80" arrivalLane="-road3_0" arrivalPos="19.96" arrivalPosLat="0.00" arrivalSpeed="10.41" duration="36.40" routeLength="206.37" waitingTime="7.20" waitingCount="1" stopTime="0.00" timeLoss="17.56" rerouteNo="1" devices="tripinfo_vehicle_111 routing_vehicle_111 emissions_vehicle_111 battery_vehicle_111" vType="human" speedFactor="0.87" vaporized="">
        <emissions CO_abs="0" CO2_abs="0" HC_abs="0" PMx_abs="0" NOx_abs="0" fuel_abs="0" electricity_abs="60.373404"/>
    </tripinfo>
    <tripinfo id="vehicle_25" depart="20.00" departLane="road1_0" departPos="4.10" departPosLat="0.00" departSpeed="0.95" departDelay="10.94" arrival="42.00" arrivalLane="-road0_0" arrivalPos="19.96" arrivalPosLat="0.00" arrivalSpeed="10.71" duration="22.00" routeLength="122.77" waitingTime="0.00" waitingCount="0" stopTime="0.00" timeLoss="10.11" rerouteNo="1" devices="tripinfo_vehicle_25 routing_vehicle_25 emissions_vehicle_25 battery_vehicle_25" vType="human" speedFactor="0.87" vaporized="">
        <emissions CO_abs="0" CO2_abs="0" HC_abs="0" PMx_abs="0" NOx_abs="0" fuel_abs="0" electricity_abs="45.437123"/>
    </tripinfo>
    <tripinfo id="vehicle_57" depart="6.40" departLane="road1_0" departPos="4.10" departPosLat="0.00" departSpeed="3.38" departDelay="1.62" arrival="42.80" arrivalLane="-road3_0" arrivalPos="19.96" arrivalPosLat="0.00" arrivalSpeed="12.41" duration="36.40" routeLength="206.37" waitingTime="6.40" waitingCount="1" stopTime="0.00" timeLoss="20.21" rerouteNo="1" devices="tripinfo_vehicle_57 routing_vehicle_57 emissions_vehicle_57 battery_vehicle_57" vType="human" speedFactor="1.14" vaporized="">
        <emissions CO_abs="0" CO2_abs="0" HC_abs="0" PMx_abs="0" NOx_abs="0" fuel_abs="0" electricity_abs="75.608990"/>
    </tripinfo>
    <tripinfo id="vehicle_55" depart="25.20" departLane="road1_0" departPos="4.10" departPosLat="0.00" departSpeed="3.33" departDelay="15.86" arrival="44.40" arrivalLane="-road0_0" arrivalPos="19.96" arrivalPosLat="0.00" arrivalSpeed="11.53" duration="19.20" routeLength="122.77" waitingTime="0.00" waitingCount="0" stopTime="0.00" timeLoss="9.06" rerouteNo="1" devices="tripinfo_vehicle_55 routing_vehicle_55 emissions_vehicle_55 battery_vehicle_55" vType="human" speedFactor="1.00" vaporized="">
        <emissions CO_abs="0" CO2_abs="0" HC_abs="0" PMx_abs="0" NOx_abs="0" fuel_abs="0" electricity_abs="49.625046"/>
    </tripinfo>
    <tripinfo id="vehicle_106" depart="8.00" departLane="road0_0" departPos="4.10" departPosLat="0.00" departSpeed="3.11" departDelay="2.96" arrival="44.40" arrivalLane="-road1_0" arrivalPos="19.96" arrivalPosLat="0.00" arrivalSpeed="12.93" duration="36.40" routeLength="289.97" waitingTime="2.00" waitingCount="1" stopTime="0.00" timeLoss="13.99" rerouteNo="0" devices="tripinfo_vehicle_106 emissions_vehicle_106 battery_vehicle_106" vType="human" speedFactor="1.01" vaporized="">
        <emissions CO_abs="0" CO2_abs="0" HC_abs="0" PMx_abs="0" NOx_abs="0" fuel_abs="0" electricity_abs="101.751599"/>
    </tripinfo>
    <tripinfo id="vehicle_67" depart="16.80" departLane="road0_0" departPos="4.10" departPosLat="0.00" departSpeed="1.19" departDelay="8.78" arrival="48.80" arrivalLane="-road1_0" arrivalPos="19.96" arrivalPosLat="0.00" arrivalSpeed="11.28" duration="32.00" routeLength="289.97" waitingTime="0.00" waitingCount="0" stopTime="0.00" timeLoss="7.70" rerouteNo="0" devices="tripinfo_vehicle_67 emissions_vehicle_67 battery_vehicle_67" vType="human" speedFactor="0.91" vaporized="">
        <emissions CO_abs="0" CO2_abs="0" HC_abs="0" PMx_abs="0" NOx_abs="0" fuel_abs="0" electricity_abs="90.391447"/>
    </tripinfo>
    <tripinfo id="vehicle_39" depart="29.60" departLane="road1_0" departPos="4.10" departPosLat="0.00" departSpeed="1.27" departDelay="19.43" arrival="49.60" arrivalLane="-road0_0" arrivalPos="19.96" arrivalPosLat="0.00" arrivalSpeed="12.47" duration="20.00" routeLength="122.77" waitingTime="0.00" waitingCount="0" stopTime="0.00" timeLoss="8.44" rerouteNo="1" devices="tripinfo_vehicle_39 routing_vehicle_39 emissions_vehicle_39 battery_vehicle_39" vType="human" speedFactor="0.90" vaporized="">
        <emissions CO_abs="0" CO2_abs="0" HC_abs="0" PMx_abs="0" NOx_abs="0" fuel_abs="0" electricity_abs="57.866182"/>
    </tripinfo>
    <tripinfo id="vehicle_9" depart="14.00" departLane="road3_0" departPos="4.10" departPosLat="0.00" departSpeed="0.99" departDelay="7.03" arrival="51.20" arrivalLane="-road2_0" arrivalPos="19.96" arrivalPosLat="0.00" arrivalSpeed="11.25" duration="37.20" routeLength="122.77" waitingTime="16.40" waitingCount="1" stopTime="0.00" timeLoss="25.29" rerouteNo="1" devices="tripinfo_vehicle_9 routing_vehicle_9 emissions_vehicle_9 battery_vehicle_9" vType="human" speedFactor="0.86" vaporized="">
        <emissions CO_abs="0" CO2_abs="0" HC_abs="0" PMx_abs="0" NOx_abs="0" fuel_abs="0" electricity_abs="54.891578"/>
    </tripinfo>
    <tripinfo id="vehicle_14" depart="19.60" departLane="road0_0" departPos="4.10" departPosLat="0.00" departSpeed="3.63" departDelay="10.94" arrival="51.20" arrivalLane="-road1_0" arrivalPos="19.96" arrivalPosLat="0.00" arrivalSpeed="11.11" duration="31.60" routeLength="289.97" waitingTime="0.00" waitingCount="0" stopTime="0.00" timeLoss="9.14" rerouteNo="0" devices="tripinfo_vehicle_14 emissions_vehicle_14 battery_vehicle_14" vType="human" speedFactor="0.99" vaporized="">
        <emissions CO_abs="0" CO2_abs="0" HC_abs="0" PMx_abs="0" NOx_abs="0" fuel_abs="0" electricity_abs="87.445482"/>
    </tripinfo>
    <tripinfo id="vehicle_31" depart="27.20" departLane="road1_0" departPos="4.10" departPosLat="0.00" departSpeed="1.60" departDelay="16.80" arrival="53.60" arrivalLane="-road3_0" arrivalPos="19.96" arrivalPosLat="0.00" arrivalSpeed="11.54" duration="26.40" routeLength="206.37" waitingTime="0.00" waitingCount="0" stopTime="0.00" timeLoss="10.19" rerouteNo="1" devices="tripinfo_vehicle_31 routing_vehicle_31 emissions_vehicle_31 battery_vehicle_31" vType="human" speedFactor="1.15" vaporized="">
        <emissions CO_abs="0" CO2_abs="0" HC_abs="0" PMx_abs="0" NOx_abs="0" fuel_abs="0" electricity_abs="73.589134"/>
    </tripinfo>
    <tripinfo id="vehicle_40" depart="8.40" departLane="road1_0" departPos="4.10" departPosLat="0.00" departSpeed="1.23" departDelay="2.91" arrival="53.60" arrivalLane="-road2_0" arrivalPos="19.96" arrivalPosLat="0.00" arrivalSpeed="12.12" duration="45.20" routeLength="289.97" waitingTime="5.60" waitingCount="1" stopTime="0.00" timeLoss="22.86" rerouteNo="1" devices="tripinfo_vehicle_40 routing_vehicle_40 emissions_vehicle_40 battery_vehicle_40" vType="human" speedFactor="1.03" vaporized="">
        <emissions CO_abs="0" CO2_abs="0" HC_abs="0" PMx_abs="0" NOx_abs="0" fuel_abs="0" electricity_abs="93.706142"/>
    </tripinfo>
    <tripinfo id="vehicle_98" depart="11.60" departLane="road3_0" departPos="4.10" departPosLat="0.00" departSpeed="2.38" departDelay="5.55" arrival="54.40" arrivalLane="-road1_0" arrivalPos="19.96" arrivalPosLat="0.00" arrivalSpeed="12.78" duration="42.80" routeLength="206.37" waitingTime="17.20" waitingCount="1" stopTime="0.00" timeLoss="26.58" rerouteNo="1" devices="tripinfo_vehicle_98 routing_vehicle_98 emissions_vehicle_98 battery_vehicle_98" vType="human" speedFactor="1.12" vaporized="">
        <emissions CO_abs="0" CO2_abs="0" HC_abs="0" PMx_abs="0" NOx_abs="0" fuel_abs="0" electricity_abs="88.359475"/>
    </tripinfo>
    <tripinfo id="vehicle_46" depart="36.00" departLane="road3_0" departPos="4.10" departPosLat="0.00" departSpeed="1.40" departDelay="29.14" arrival="55.60" arrivalLane="-road2_0" arrivalPos="19.96" arrivalPosLat="0.00" arrivalSpeed="12.37" duration="19.60" routeLength="122.77" waitingTime="0.00" waitingCount="0" stopTime="0.00" timeLoss="9.33" rerouteNo="1" devices="tripinfo_vehicle_46 routing_vehicle_46 emissions_vehicle_46 battery_vehicle_46" vType="human" speedFactor="1.00" vaporized="">
        <emissions CO_abs="0" CO2_abs="0" HC_abs="0" PMx_abs="0" NOx_abs="0" fuel_abs="0" electricity_abs="58.168847"/>
    </tripinfo>
    <tripinfo id="vehicle_66" depart="38.80" departLane="road1_0" departPos="4.10" departPosLat="0.00" departSpeed="2.99" departDelay="21.22" arrival="56.40" arrivalLane="-road0_0" arrivalPos="19.96" arrivalPosLat="0.00" arrivalSpeed="11.73" duration="17.60" routeLength="122.77" waitingTime="0.00" waitingCount="0" stopTime="0.00" timeLoss="6.32" rerouteNo="1" devices="tripinfo_vehicle_66 routing_vehicle_66 emissions_vehicle_66 battery_vehicle_66" vType="human" speedFactor="0.91" vaporized="">
        <emissions CO_abs="0" CO2_abs="0" HC_abs="0" PMx_abs="0" NOx_abs="0" fuel_abs="0" electricity_abs="53.872760"/>
    </tripinfo>
    <tripinfo id="vehicle_64" depart="22.80" departLane="road1_0" departPos="4.10" departPosLat="0.00" departSpeed="1.77" departDelay="13.64" arrival="58.40" arrivalLane="-road2_0" arrivalPos="19.96" arrivalPosLat="0.00" arrivalSpeed="10.94" duration="35.60" routeLength="289.97" waitingTime="0.00" waitingCount="0" stopTime="0.00" timeLoss="11.92" rerouteNo="1" devices="tripinfo_vehicle_64 routing_vehicle_64 emissions_vehicle_64 battery_vehicle_64" vType="human" speedFactor="0.94" vaporized="">
        <emissions CO_abs="0" CO2_abs="0" HC_abs="0" PMx_abs="0" NOx_abs="0" fuel_abs="0" electricity_abs="84.756453"/>
    </tripinfo>
    <tripinfo id="vehicle_69" depart="6.80" departLane="road2_0" departPos="4.10" departPosLat="0.00" departSpeed="1.66" departDelay="4.77" arrival="58.40" arrivalLane="-road1_0" arrivalPos="19.96" arrivalPosLat="0.00" arrivalSpeed="12.13" duration="51.60" routeLength="122.77" waitingTime="32.80" waitingCount="1" stopTime="0.00" timeLoss="41.14" rerouteNo="1" devices="tripinfo_vehicle_69 routing_vehicle_69 emissions_vehicle_69 battery_vehicle_69" vType="human" speedFactor="1.02" vaporized="">
        <emissions CO_abs="0" CO2_abs="0" HC_abs="0" PMx_abs="0" NOx_abs="0" fuel_abs="0" electricity_abs="63.515054"/>
    </tripinfo>
    <tripinfo id="vehicle_77" depart="32.00" departLane="road1_0" departPos="4.10" departPosLat="0.00" departSpeed="2.23" departDelay="20.67" arrival="59.20" arrivalLane="-road3_0" arrivalPos="19.96" arrivalPosLat="0.00" arrivalSpeed="12.63" duration="27.20" routeLength="206.37" waitingTime="0.00" waitingCount="0" stopTime="0.00" timeLoss="10.39" rerouteNo="1" devices="tripinfo_vehicle_77 routing_vehicle_77 emissions_vehicle_77 battery_vehicle_77" vType="human" speedFactor="0.98" vaporized="">
        <emissions CO_abs="0" CO2_abs="0" HC_abs="0" PMx_abs="0" NOx_abs="0" fuel_abs="0" electricity_abs="77.676204"/>
    </tripinfo>
    <tripinfo id="vehicle_87" depart="41.20" departLane="road1_0" departPos="4.10" departPosLat="0.00" departSpeed="2.61" departDelay="23.38" arrival="59.20" arrivalLane="-road0_0" arrivalPos="19.96" arrivalPosLat="0.00" arrivalSpeed="11.76" duration="18.00" routeLength="122.77" waitingTime="0.00" waitingCount="0" stopTime="0.00" timeLoss="7.57" rerouteNo="1" devices="tripinfo_vehicle_87 routing_vehicle_87 emissions_vehicle_87 battery_vehicle_87" vType="human" speedFactor="1.04" vaporized="">
        <emissions CO_abs="0" CO2_abs="0" HC_abs="0" PMx_abs="0" NOx_abs="0" fuel_abs="0" electricity_abs="54.552944"/>
    </tripinfo>
    <tripinfo id="vehicle_88" depart="10.00" departLane="road3_0" departPos="4.10" departPosLat="0.00" departSpeed="3.64" departDelay="4.92" arrival="61.20" arrivalLane="-road0_0" arrivalPos="19.96" arrivalPosLat="0.00" arrivalSpeed="12.82" duration="51.20" routeLength="289.97" waitingTime="18.80" waitingCount="1" stopTime="0.00" timeLoss="28.70" rerouteNo="1" devices="tripinfo_vehicle_88 routing_vehicle_88 emissions_vehicle_88 battery_vehicle_88" vType="human" speedFactor="1.01" vaporized="">
        <emissions CO_abs="0" CO2_abs="0" HC_abs="0" PMx_abs="0" NOx_abs="0" fuel_abs="0" electricity_abs="102.268788"/>
    </tripinfo>
    <tripinfo id="vehicle_81" depart="11.60" departLane="road2_0" departPos="4.10" departPosLat="0.00" departSpeed="1.30" departDelay="8.86" arrival="62.40" arrivalLane="-road1_0" arrivalPos="19.96" arrivalPosLat="0.00" arrivalSpeed="12.56" duration="50.80" routeLength="122.77" waitingTime="30.40" waitingCount="2" stopTime="0.00" timeLoss="40.28" rerouteNo="1" devices="tripinfo_vehicle_81 routing_vehicle_81 emissions_vehicle_81 battery_vehicle_81" vType="human" speedFactor="1.00" vaporized="">
        <emissions CO_abs="0" CO2_abs="0" HC_abs="0" PMx_abs="0" NOx_abs="0" fuel_abs="0" electricity_abs="65.603954"/>
    </tripinfo>
    <tripinfo id="vehicle_75" depart="42.80" departLane="road3_0" departPos="4.10" departPosLat="0.00" departSpeed="2.51" departDelay="33.52" arrival="64.80" arrivalLane="-road2_0" arrivalPos="19.96" arrivalPosLat="0.00" arrivalSpeed="12.50" duration="22.00" routeLength="122.77" waitingTime="0.00" waitingCount="0" stopTime="0.00" timeLoss="11.43" rerouteNo="1" devices="tripinfo_vehicle_75 routing_vehicle_75 emissions_vehicle_75 battery_vehicle_75" vType="human" speedFactor="0.98" vaporized="">
        <emissions CO_abs="0" CO2_abs="0" HC_abs="0" PMx_abs="0" NOx_abs="0" fuel_abs="0" electricity_abs="55.263278"/>
    </tripinfo>
    <tripinfo id="vehicle_89" depart="45.60" departLane="road1_0" departPos="4.10" departPosLat="0.00" departSpeed="1.83" departDelay="26.12" arrival="65.60" arrivalLane="-road0_0" arrivalPos="19.96" arrivalPosLat="0.00" arrivalSpeed="12.41" duration="20.00" routeLength="122.77" waitingTime="0.00" waitingCount="0" stopTime="0.00" timeLoss="9.65" rerouteNo="1" devices="tripinfo_vehicle_89 routing_vehicle_89 emissions_vehicle_89 battery_vehicle_89" vType="human" speedFactor="1.02" vaporized="">
        <emissions CO_abs="0" CO2_abs="0" HC_abs="0" PMx_abs="0" NOx_abs="0" fuel_abs="0" electricity_abs="58.061218"/>
    </tripinfo>
    <tripinfo id="vehicle_119" depart="44.80" departLane="road3_0" departPos="4.10" departPosLat="0.00" departSpeed="2.30" departDelay="33.65" arrival="66.80" arrivalLane="-road2_0" arrivalPos="19.96" arrivalPosLat="0.00" arrivalSpeed="12.12" duration="22.00" routeLength="122.77" waitingTime="0.00" waitingCount="0" stopTime="0.00" timeLoss="11.79" rerouteNo="1" devices="tripinfo_vehicle_119 routing_vehicle_119 emissions_vehicle_119 battery_vehicle_119" vType="human" speedFactor="1.07" vaporized="">
        <emissions CO_abs="0" CO2_abs="0" HC_abs="0" PMx_abs="0" NOx_abs="0" fuel_abs="0" electricity_abs="53.410527"/>
    </tripinfo>
    <tripinfo id="vehicle_27" depart="38.80" departLane="road3_0" departPos="4.10" departPosLat="0.00" departSpeed="2.99" departDelay="29.68" arrival="69.20" arrivalLane="-road1_0" arrivalPos="19.96" arrivalPosLat="0.00" arrivalSpeed="11.26" duration="30.40" routeLength="206.37" waitingTime="0.00" waitingCount="0" stopTime="0.00" timeLoss="13.22" rerouteNo="1" devices="tripinfo_vehicle_27 routing_vehicle_27 emissions_vehicle_27 battery_vehicle_27" vType="human" speedFactor="0.95" vaporized="">
        <emissions CO_abs="0" CO2_abs="0" HC_abs="0" PMx_abs="0" NOx_abs="0" fuel_abs="0" electricity_abs="63.887911"/>
    </tripinfo>
    <tripinfo id="vehicle_34" depart="40.80" departLane="road3_0" departPos="4.10" departPosLat="0.00" departSpeed="2.51" departDelay="31.49" arrival="71.20" arrivalLane="-road1_0" arrivalPos="19.96" arrivalPosLat="0.00" arrivalSpeed="13.23" duration="30.40" routeLength="206.37" waitingTime="0.00" waitingCount="0" stopTime="0.00" timeLoss="13.88" rerouteNo="1" devices="tripinfo_vehicle_34 routing_vehicle_34 emissions_vehicle_34 battery_vehicle_34" vType="human" speedFactor="0.99" vaporized="">
        <emissions CO_abs="0" CO2_abs="0" HC_abs="0" PMx_abs="0" NOx_abs="0" fuel_abs="0" electricity_abs="77.162607"/>
    </tripinfo>
    <tripinfo id="vehicle_85" depart="43.60" departLane="road1_0" departPos="4.10" departPosLat="0.00" departSpeed="3.65" departDelay="24.86" arrival="72.40" arrivalLane="-road3_0" arrivalPos="19.96" arrivalPosLat="0.00" arrivalSpeed="11.45" duration="28.80" routeLength="206.37" waitingTime="0.00" waitingCount="0" stopTime="0.00" timeLoss="11.81" rerouteNo="1" devices="tripinfo_vehicle_85 routing_vehicle_85 emissions_vehicle_85 battery_vehicle_85" vType="human" speedFactor="0.98" vaporized="">
        <emissions CO_abs="0" CO2_abs="0" HC_abs="0" PMx_abs="0" NOx_abs="0" fuel_abs="0" electricity_abs="66.732688"/>
    </tripinfo>
    <tripinfo id="vehicle_5" depart="34.40" departLane="road1_0" departPos="4.10" departPosLat="0.00" departSpeed="2.83" departDelay="22.03" arrival="72.80" arrivalLane="-road2_0" arrivalPos="19.96" arrivalPosLat="0.00" arrivalSpeed="11.18" duration="38.40" routeLength="289.97" waitingTime="0.00" waitingCount="0" stopTime="0.00" timeLoss="11.45" rerouteNo="1" devices="tripinfo_vehicle_5 routing_vehicle_5 emissions_vehicle_5 battery_vehicle_5" vType="human" speedFactor="0.83" vaporized="">
        <emissions CO_abs="0" CO2_abs="0" HC_abs="0" PMx_abs="0" NOx_abs="0" fuel_abs="0" electricity_abs="76.804873"/>
    </tripinfo>
    <tripinfo id="vehicle_19" depart="47.20" departLane="road3_0" departPos="4.10" departPosLat="0.00" departSpeed="0.83" departDelay="35.35" arrival="73.20" arrivalLane="-road1_0" arrivalPos="19.96" arrivalPosLat="0.00" arrivalSpeed="12.06" duration="26.00" routeLength="206.37" waitingTime="0.00" waitingCount="0" stopTime="0.00" timeLoss="9.95" rerouteNo="1" devices="tripinfo_vehicle_19 routing_vehicle_19 emissions_vehicle_19 battery_vehicle_19" vType="human" speedFactor="1.16" vaporized="">
        <emissions CO_abs="0" CO2_abs="0" HC_abs="0" PMx_abs="0" NOx_abs="0" fuel_abs="0" electricity_abs="77.801505"/>
    </tripinfo>
    <tripinfo id="vehicle_78" depart="9.20" departLane="road2_0" departPos="4.10" departPosLat="0.00" departSpeed="1.66" departDelay="7.16" arrival="74.40" arrivalLane="-road3_0" arrivalPos="19.96" arrivalPosLat="0.00" arrivalSpeed="12.45" duration="65.20" routeLength="289.97" waitingTime="31.60" waitingCount="1" stopTime="0.00" timeLoss="42.61" rerouteNo="1" devices="tripinfo_vehicle_78 routing_vehicle_78 emissions_vehicle_78 battery_vehicle_78" vType="human" speedFactor="1.01" vaporized="">
        <emissions CO_abs="0" CO2_abs="0" HC_abs="0" PMx_abs="0" NOx_abs="0" fuel_abs="0" electricity_abs="102.095243"/>
    </tripinfo>
    <tripinfo id="vehicle_102" depart="36.40" departLane="road1_0" departPos="4.10" departPosLat="0.00" departSpeed="1.98" departDelay="22.19" arrival="74.80" arrivalLane="-road2_0" arrivalPos="19.96" arrivalPosLat="0.00" arrivalSpeed="12.05" duration="38.40" routeLength="289.97" waitingTime="0.00" waitingCount="0" stopTime="0.00" timeLoss="15.44" rerouteNo="1" devices="tripinfo_vehicle_102 routing_vehicle_102 emissions_vehicle_102 battery_vehicle_102" vType="human" speedFactor="0.97" vaporized="">
        <emissions CO_abs="0" CO2_abs="0" HC_abs="0" PMx_abs="0" NOx_abs="0" fuel_abs="0" electricity_abs="83.979512"/>
    </tripinfo>
    <tripinfo id="vehicle_60" depart="48.00" departLane="road1_0" departPos="4.10" departPosLat="0.00" departSpeed="2.60" departDelay="28.17" arrival="76.80" arrivalLane="-road3_0" arrivalPos="19.96" arrivalPosLat="0.00" arrivalSpeed="13.85" duration="28.80" routeLength="206.37" waitingTime="0.00" waitingCount="0" stopTime="0.00" timeLoss="12.34" rerouteNo="1" devices="tripinfo_vehicle_60 routing_vehicle_60 emissions_vehicle_60 battery_vehicle_60" vType="human" speedFactor="1.08" vaporized="">
        <emissions CO_abs="0" CO2_abs="0" HC_abs="0" PMx_abs="0" NOx_abs="0" fuel_abs="0" electricity_abs="82.483995"/>
    </tripinfo>
    <tripinfo id="vehicle_110" depart="51.60" departLane="road3_0" departPos="4.10" departPosLat="0.00" departSpeed="3.43" departDelay="38.94" arrival="77.20" arrivalLane="-road2_0" arrivalPos="19.96" arrivalPosLat="0.00" arrivalSpeed="11.67" duration="25.60" routeLength="122.77" waitingTime="2.00" waitingCount="1" stopTime="0.00" timeLoss="14.26" rerouteNo="1" devices="tripinfo_vehicle_110 routing_vehicle_110 emissions_vehicle_110 battery_vehicle_110" vType="human" speedFactor="0.93" vaporized="">
        <emissions CO_abs="0" CO2_abs="0" HC_abs="0" PMx_abs="0" NOx_abs="0" fuel_abs="0" electricity_abs="50.492263"/>
    </tripinfo>
    <tripinfo id="vehicle_114" depart="57.20" departLane="road1_0" departPos="4.10" departPosLat="0.00" departSpeed="2.77" departDelay="35.29" arrival="77.60" arrivalLane="-road0_0" arrivalPos="19.96" arrivalPosLat="0.00" arrivalSpeed="12.87" duration="20.40" routeLength="122.77" waitingTime="1.20" waitingCount="1" stopTime="0.00" timeLoss="10.22" rerouteNo="1" devices="tripinfo_vehicle_114 routing_vehicle_114 emissions_vehicle_114 battery_vehicle_114" vType="human" speedFactor="1.10" vaporized="">
        <emissions CO_abs="0" CO2_abs="0" HC_abs="0" PMx_abs="0" NOx_abs="0" fuel_abs="0" electricity_abs="64.958863"/>
    </tripinfo>
    <tripinfo id="vehicle_65" depart="49.20" departLane="road3_0" departPos="4.10" departPosLat="0.00" departSpeed="2.37" departDelay="37.46" arrival="78.00" arrivalLane="-road1_0" arrivalPos="19.96" arrivalPosLat="0.00" arrivalSpeed="12.07" duration="28.80" routeLength="206.37" waitingTime="0.00" waitingCount="0" stopTime="0.00" timeLoss="10.08" rerouteNo="1" devices="tripinfo_vehicle_65 routing_vehicle_65 emissions_vehicle_65 battery_vehicle_65" vType="human" speedFactor="0.88" vaporized="">
        <emissions CO_abs="0" CO2_abs="0" HC_abs="0" PMx_abs="0" NOx_abs="0" fuel_abs="0" electricity_abs="70.160472"/>
    </tripinfo>
    <tripinfo id="rl_0" depart="50.00" departLane="road1_0" departPos="4.10" departPosLat="0.00" departSpeed="2.76" departDelay="30.16" arrival="79.20" arrivalLane="-road3_0" arrivalPos="19.96" arrivalPosLat="-0.00" arrivalSpeed="7.08" duration="29.20" routeLength="206.37" waitingTime="0.00" waitingCount="0" stopTime="0.00" timeLoss="11.86" rerouteNo="1" devices="tripinfo_rl_0 routing_rl_0 emissions_rl_0 battery_rl_0 driverstaterl_0" vType="rlAnget" speedFactor="0.94" vaporized="">
        <emissions CO_abs="0" CO2_abs="0" HC_abs="0" PMx_abs="0" NOx_abs="0" fuel_abs="0" electricity_abs="44.116666"/>
    </tripinfo>
</tripinfos>
